xpycommon/__init__.py
xpycommon/bonfire.py
xpycommon/common.py
xpycommon/enum.py
xpycommon/exception.py
xpycommon/libc_wrapper.py
xpycommon/log.py
xpycommon/plugin.py
xpycommon/random.py
xpycommon/types.py
xpycommon/uuid.py
xpycommon/android/__init__.py
xpycommon/android/android.py
xpycommon/android/exception.py
xpycommon/at_cmd/__init__.py
xpycommon/at_cmd/at_cmd.py
xpycommon/bluetooth/__init__.py
xpycommon/bluetooth/bluetooth.py
xpycommon/bluetooth/exception.py
xpycommon/bluetooth/android/__init__.py
xpycommon/bluetooth/android/android.py
xpycommon/bluetooth/android/btsnoop_live.py
xpycommon/bluetooth/android/btsnooz.py
xpycommon/bluetooth/bluez/__init__.py
xpycommon/bluetooth/bluez/bt_agent.py
xpycommon/bluetooth/bluez/exception.py
xpycommon/bluetooth/bluez/spoof.py
xpycommon/bluetooth/bluez/systemd_service.py
xpycommon/cmdline_arg_converter/__init__.py
xpycommon/cmdline_arg_converter/cmdline_arg_converter.py
xpycommon/dbus/__init__.py
xpycommon/dbus/dbus.py
xpycommon/pytransform/__init__.py
xpycommon/pytransform/platforms/linux/aarch64/_pytransform.so
xpycommon/pytransform/platforms/linux/x86_64/_pytransform.so
xpycommon/res/oui.txt
xpycommon/ui/__init__.py
xpycommon/ui/ui.py
xpycommon-0.0.25.dist-info/LICENSE.txt
xpycommon-0.0.25.dist-info/METADATA
xpycommon-0.0.25.dist-info/WHEEL
xpycommon-0.0.25.dist-info/top_level.txt
xpycommon-0.0.25.dist-info/RECORD
